ellar_cli/__init__.py
ellar_cli/__main__.py
ellar_cli/cli.py
ellar_cli/constants.py
ellar_cli/file_scaffolding.py
ellar_cli/main.py
ellar_cli/py.typed
ellar_cli/schema.py
ellar_cli/testing.py
ellar_cli/click/__init__.py
ellar_cli/click/argument.py
ellar_cli/click/command.py
ellar_cli/click/group.py
ellar_cli/click/util.py
ellar_cli/manage_commands/__init__.py
ellar_cli/manage_commands/create_module.py
ellar_cli/manage_commands/create_project.py
ellar_cli/manage_commands/new.py
ellar_cli/manage_commands/runserver.py
ellar_cli/scaffolding/__init__.py
ellar_cli/scaffolding/scaffolding_json_validator.py
ellar_cli/scaffolding/module_template/setup.json
ellar_cli/scaffolding/module_template/module_name/__init__.ellar
ellar_cli/scaffolding/module_template/module_name/controllers.ellar
ellar_cli/scaffolding/module_template/module_name/module.ellar
ellar_cli/scaffolding/module_template/module_name/routers.ellar
ellar_cli/scaffolding/module_template/module_name/schemas.ellar
ellar_cli/scaffolding/module_template/module_name/services.ellar
ellar_cli/scaffolding/module_template/module_name/tests/__init__.ellar
ellar_cli/scaffolding/module_template/module_name/tests/test_controllers.ellar
ellar_cli/scaffolding/module_template/module_name/tests/test_routers.ellar
ellar_cli/scaffolding/module_template/module_name/tests/test_services.ellar
ellar_cli/scaffolding/new_manage_template/setup.json
ellar_cli/scaffolding/new_manage_template/folder_name/README.md
ellar_cli/scaffolding/new_manage_template/folder_name/manage.ellar
ellar_cli/scaffolding/new_manage_template/folder_name/tests/conftest.ellar
ellar_cli/scaffolding/new_template/setup.json
ellar_cli/scaffolding/new_template/folder_name/README.md
ellar_cli/scaffolding/new_template/folder_name/pyproject.toml
ellar_cli/scaffolding/new_template/folder_name/tests/conftest.ellar
ellar_cli/scaffolding/project_template/setup.json
ellar_cli/scaffolding/project_template/project_name/__init__.ellar
ellar_cli-0.4.4.dist-info/entry_points.txt
ellar_cli-0.4.4.dist-info/licenses/LICENSE
ellar_cli-0.4.4.dist-info/WHEEL
ellar_cli-0.4.4.dist-info/METADATA
ellar_cli-0.4.4.dist-info/RECORD
