Metadata-Version: 2.4
Name: ellar-cli
Version: 0.4.4
Summary: Ellar CLI Tool for Scaffolding Ellar Projects, Modules and also running Ellar Commands
Author-email: Ezeudoh Tochukwu <tochukwu.ezeudoh@gmail.com>
Requires-Python: >=3.8
Classifier: Intended Audience :: Information Technology
Classifier: Intended Audience :: System Administrators
Classifier: Operating System :: OS Independent
Classifier: Topic :: Internet
Classifier: Topic :: Software Development :: Libraries :: Application Frameworks
Classifier: Topic :: Software Development :: Libraries :: Python Modules
Classifier: Topic :: Software Development :: Libraries
Classifier: Topic :: Software Development
Classifier: Typing :: Typed
Classifier: Environment :: Web Environment
Classifier: Intended Audience :: Developers
Classifier: License :: OSI Approved :: MIT License
Classifier: Programming Language :: Python :: 3
Classifier: Programming Language :: Python :: 3.8
Classifier: Programming Language :: Python :: 3.9
Classifier: Programming Language :: Python :: 3.10
Classifier: Programming Language :: Python :: 3.11
Classifier: Programming Language :: Python :: 3 :: Only
Classifier: Framework :: AsyncIO
Classifier: Topic :: Internet :: WWW/HTTP :: HTTP Servers
Classifier: Topic :: Internet :: WWW/HTTP
License-File: LICENSE
Requires-Dist: tomlkit >=0.11.1,<1.0.0,!=0.11.2,!=0.11.3
Requires-Dist: ellar >= 0.8.1
Requires-Dist: uvicorn[standard] == 0.37.0
Requires-Dist: click >= 8.1.8
Project-URL: Documentation, https://github.com/python-ellar/ellar-cli
Project-URL: Homepage, https://python-ellar.github.io/ellar-cli/
Project-URL: Source, https://github.com/python-ellar/ellar-cli
